aiu_fms_testing_utils/__init__.py
aiu_fms_testing_utils/_version.py
aiu_fms_testing_utils/scripts/README.md
aiu_fms_testing_utils/scripts/drive_paged_programs.py
aiu_fms_testing_utils/scripts/generate_layers_metrics.py
aiu_fms_testing_utils/scripts/generate_metrics.py
aiu_fms_testing_utils/scripts/inference.py
aiu_fms_testing_utils/scripts/run_encoders.py
aiu_fms_testing_utils/scripts/save_cpu_data.py
aiu_fms_testing_utils/scripts/small-toy.py
aiu_fms_testing_utils/scripts/validation.py
aiu_fms_testing_utils/testing/__init__.py
aiu_fms_testing_utils/testing/utils.py
aiu_fms_testing_utils/testing/validation.py
aiu_fms_testing_utils/utils/__init__.py
aiu_fms_testing_utils/utils/aiu_setup.py
aiu_fms_testing_utils/utils/args_parsing.py
aiu_fms_testing_utils/utils/dpp_config.py
aiu_fms_testing_utils/utils/encoders_utils.py
aiu_fms_testing_utils/utils/env_utils.py
aiu_fms_testing_utils/utils/metrics_utils.py
aiu_fms_testing_utils/utils/model_setup.py
aiu_fms_testing_utils/utils/paged.py
aiu_fms_testing_utils/utils/quantization_setup.py
aiu_fms_testing_utils-0.6.0.dist-info/licenses/LICENSE
aiu_fms_testing_utils-0.6.0.dist-info/METADATA
aiu_fms_testing_utils-0.6.0.dist-info/WHEEL
aiu_fms_testing_utils-0.6.0.dist-info/entry_points.txt
aiu_fms_testing_utils-0.6.0.dist-info/top_level.txt
aiu_fms_testing_utils-0.6.0.dist-info/RECORD
