Metadata-Version: 2.4
Name: aiu-fms-testing-utils
Version: 0.6.0
Summary: Spyre FMS Testing Utils
Author-email: Thara Palanivel <tpalan@ibm.com>, Joshua Rosenkranz <jmrosenk@us.ibm.com>, Antoni Viros i Martin <aviros@ibm.com>
License-Expression: Apache-2.0
Project-URL: Homepage, https://github.com/foundation-model-stack/aiu-fms-testing-utils
Project-URL: Repository, https://github.com/foundation-model-stack/aiu-fms-testing-utils
Project-URL: Issues, https://github.com/foundation-model-stack/aiu-fms-testing-utils/issues
Keywords: aiu-fms-testing-utils,python,utils
Classifier: Development Status :: 3 - Alpha
Classifier: Environment :: Console
Classifier: Intended Audience :: Developers
Classifier: Intended Audience :: Science/Research
Classifier: Operating System :: OS Independent
Classifier: Programming Language :: Python
Classifier: Programming Language :: Python :: 3
Classifier: Programming Language :: Python :: 3.12
Classifier: Topic :: Scientific/Engineering
Classifier: Topic :: Scientific/Engineering :: Artificial Intelligence
Classifier: Topic :: Software Development :: Testing
Classifier: Topic :: Software Development :: Testing :: Unit
Classifier: Topic :: Software Development :: Libraries :: Python Modules
Requires-Python: <3.13,>=3.11
License-File: LICENSE
Requires-Dist: ibm-fms<2.0,>=1.1.0
Requires-Dist: fms-model-optimizer[fp8]<1.0,>=0.5.0
Requires-Dist: sentencepiece<0.3.0,>=0.2.0
Requires-Dist: numpy<2.3.0,>=1.26.4
Requires-Dist: transformers<=4.58,>=4.45
Requires-Dist: torch==2.7.1
Provides-Extra: dev
Requires-Dist: wheel<1.0,>=0.42.0; extra == "dev"
Requires-Dist: packaging<25,>=23.2; extra == "dev"
Dynamic: license-file
